request_sign/__init__.py
request_sign/middleware.py
request_sign/settings.py
request_sign/signature.py
request_sign/utils.py
django_request_sign-1.1.5.dist-info/METADATA
django_request_sign-1.1.5.dist-info/WHEEL
django_request_sign-1.1.5.dist-info/top_level.txt
django_request_sign-1.1.5.dist-info/RECORD
