Metadata-Version: 2.1
Name: django-request-sign
Version: 1.1.5
Summary: django request signature
Home-page: https://github.com/liyao2598330/django-request-sign
Author: liyao
Author-email: liyao2598330@126.com
License: UNKNOWN
Platform: UNKNOWN
Classifier: Programming Language :: Python :: 3
Classifier: License :: OSI Approved :: MIT License
Requires-Python: >=3
